ezviz_openapi_utils/__init__.py
ezviz_openapi_utils/api.py
ezviz_openapi_utils/client.py
ezviz_openapi_utils/exceptions.py
ezviz_openapi_utils/oauth.py
ezviz_openapi_utils-0.3.4.dist-info/licenses/LICENSE
ezviz_openapi_utils-0.3.4.dist-info/METADATA
ezviz_openapi_utils-0.3.4.dist-info/WHEEL
ezviz_openapi_utils-0.3.4.dist-info/top_level.txt
ezviz_openapi_utils-0.3.4.dist-info/RECORD
