Metadata-Version: 2.4
Name: ezviz-openapi-utils
Version: 0.3.4
Summary: A Python library for the EZVIZ OpenAPI platform, handling authentication and API requests.
Author-email: SunBo <1443584939@qq.com>
Project-URL: Homepage, https://github.com/sunbos/ezviz-openapi-utils
Project-URL: Bug Tracker, https://github.com/sunbos/ezviz-openapi-utils/issues
Classifier: Programming Language :: Python :: 3.8
Classifier: Programming Language :: Python :: 3.9
Classifier: Programming Language :: Python :: 3.10
Classifier: Programming Language :: Python :: 3.11
Classifier: Programming Language :: Python :: 3.12
Classifier: License :: OSI Approved :: MIT License
Classifier: Operating System :: OS Independent
Requires-Python: >=3.8
License-File: LICENSE
Requires-Dist: requests
Provides-Extra: dev
Requires-Dist: pytest; extra == "dev"
Requires-Dist: python-dotenv; extra == "dev"
Dynamic: license-file
